Workbook
Name Investimento_Mensal: Simulador!$C$14
Name Qntd_anos: Simulador!$C$15
Name Rendimento_Carteira: Simulador!$C$8
Name Salario: Simulador!$C$7
Name Sugestãp_Investimento: Simulador!$B$9
Name Taxa_Mensal: Simulador!$C$16
Name Taxa_Rendimento_Mensal: Simulador!$C$16

Sheet Simulador
A1: Santos Investimentos
B6: Configurações
B7: Salário | C7: 2800
B8: Rendimento Carteira | C8: 0.0089
B9: Sugestão de Investimento | C9: =C7*30% -> 840
B13: Investimento Mensal
B14: Quanto investir por mês ? | C14: 230
B15: Por Quantos Anos ? | C15: 5
B16: Taxa de Rendimento mensal ? | C16: 0.01079
B17: Patrimônio acumulado ? | C17: =FV(Taxa_Mensal,Qntd_anos*12,Investimento_Mensal*-1) -> 19268.69
B18: Dividendos Mensais ? | C18: =C17*Rendimento_Carteira -> 171.49134
B20: Cenário Patrimônio | D20: Dividendos
A21: 2 | B21: Quanto em 2 anos? | C21: =FV(Taxa_Mensal,$A21*12,Investimento_Mensal*-1) -> 6262.3543 | D21: =C21*Rendimento_Carteira -> 55.734953
A22: 5 | B22: Quanto em 5 anos? | C22: =FV(Taxa_Mensal,$A22*12,Investimento_Mensal*-1) -> 19268.69 | D22: =C22*Rendimento_Carteira -> 171.49134
A23: 10 | B23: Quanto em 10 anos? | C23: =FV(Taxa_Mensal,$A23*12,Investimento_Mensal*-1) -> 55955.369 | D23: =C23*Rendimento_Carteira -> 498.00278
A24: 20 | B24: Quanto em 20 anos? | C24: =FV(Taxa_Mensal,$A24*12,Investimento_Mensal*-1) -> 258795.63 | D24: =C24*Rendimento_Carteira -> 2303.2811
A25: 30 | B25: Quanto em 30 anos? | C25: =FV(Taxa_Mensal,$A25*12,Investimento_Mensal*-1) -> 994099.02 | D25: =C25*Rendimento_Carteira -> 8847.4813
B27: Perfil | C27: Moderado
B28: Valor a ser Investido Mensal | C28: =Investimento_Mensal -> 230
B30: Tipo de FII | C30: Percentual Sugerido | D30: Valores
B31: Desenvolvimento | C31: =VLOOKUP($C$27&"-"&B31,Dados!A:D,4,FALSE) -> 0.1 | D31: =C31*$C$28 -> 23
B32: FOFs | C32: =VLOOKUP($C$27&"-"&B32,Dados!A:D,4,FALSE) -> 0.05 | D32: =C32*$C$28 -> 11.5
B33: Híbridos | C33: =VLOOKUP($C$27&"-"&B33,Dados!A:D,4,FALSE) -> 0.08 | D33: =C33*$C$28 -> 18.4
B34: Hotelarias | C34: =VLOOKUP($C$27&"-"&B34,Dados!A:D,4,FALSE) -> 0.1 | D34: =C34*$C$28 -> 23
B35: Papel | C35: =VLOOKUP($C$27&"-"&B35,Dados!A:D,4,FALSE) -> 0.32 | D35: =C35*$C$28 -> 73.6
B36: Tijolo | C36: =VLOOKUP($C$27&"-"&B36,Dados!A:D,4,FALSE) -> 0.35 | D36: =C36*$C$28 -> 80.5
B37: TOTAL | D37: =SUM(D31:D36) -> 230

Sheet Dados
A1: CHAVE | B1: PERFIL | C1: TIPO DE FII | D1: %
A2: =$B$2&"-"&C2 -> Conservador-PAPEL | B2: Conservador | C2: PAPEL | D2: 0.3
A3: =$B$2&"-"&C3 -> Conservador-TIJOLO | B3: Conservador | C3: TIJOLO | D3: 0.5
A4: =$B$2&"-"&C4 -> Conservador-HÍBRIDOS | B4: Conservador | C4: HÍBRIDOS | D4: 0.1
A5: =$B$2&"-"&C5 -> Conservador-FOFs | B5: Conservador | C5: FOFs | D5: 0.1
A6: =$B$2&"-"&C6 -> Conservador-DESENVOLVIMENTO | B6: Conservador | C6: DESENVOLVIMENTO | D6: 0
A7: =$B$2&"-"&C7 -> Conservador-HOTELARIAS | B7: Conservador | C7: HOTELARIAS | D7: 0
A8: =$B$8&"-"&C8 -> Moderado-PAPEL | B8: Moderado | C8: PAPEL | D8: 0.32
A9: =$B$8&"-"&C9 -> Moderado-TIJOLO | B9: Moderado | C9: TIJOLO | D9: 0.35
A10: =$B$8&"-"&C10 -> Moderado-HÍBRIDOS | B10: Moderado | C10: HÍBRIDOS | D10: 0.08
A11: =$B$8&"-"&C11 -> Moderado-FOFs | B11: Moderado | C11: FOFs | D11: 0.05
A12: =$B$8&"-"&C12 -> Moderado-DESENVOLVIMENTO | B12: Moderado | C12: DESENVOLVIMENTO | D12: 0.1
A13: =$B$8&"-"&C13 -> Moderado-HOTELARIAS | B13: Moderado | C13: HOTELARIAS | D13: 0.1
A14: =$B$14&"-"&C14 -> Agressivo-PAPEL | B14: Agressivo | C14: PAPEL | D14: 0.5
A15: =$B$14&"-"&C15 -> Agressivo-TIJOLO | B15: Agressivo | C15: TIJOLO | D15: 0.1
A16: =$B$14&"-"&C16 -> Agressivo-HÍBRIDOS | B16: Agressivo | C16: HÍBRIDOS | D16: 0.05
A17: =$B$14&"-"&C17 -> Agressivo-FOFs | B17: Agressivo | C17: FOFs | D17: 0.05
A18: =$B$14&"-"&C18 -> Agressivo-DESENVOLVIMENTO | B18: Agressivo | C18: DESENVOLVIMENTO | D18: 0.2
A19: =$B$14&"-"&C19 -> Agressivo-HOTELARIAS | B19: Agressivo | C19: HOTELARIAS | D19: 0.1
